[
  {
    "op": "remove",
    "path": "/items/w1/config/times/y"
  },
  {
    "op": "add",
    "path": "/items/w1/config/times/x",
    "value": 2
  },
  {
    "op": "replace",
    "path": "/items/w1/config/direction",
    "value": "towards"
  },
  {
    "op": "remove",
    "path": "/items/w/config/times/x"
  },
  {
    "op": "add",
    "path": "/items/w/config/times/y",
    "value": 6
  },
  {
    "op": "replace",
    "path": "/items/w/config/direction",
    "value": "right"
  },
  {
    "op": "add",
    "path": "/items/b8",
    "value": {
      "config": {
        "style": "organic"
      },
      "position": {
        "x": 3,
        "y": 5,
        "z": 0
      },
      "type": "block"
    }
  },
  {
    "op": "add",
    "path": "/items/b9",
    "value": {
      "config": {
        "style": "organic"
      },
      "position": {
        "x": 1,
        "y": 5,
        "z": 0
      },
      "type": "block"
    }
  }
]
